PartyBotPackage/__init__.py
PartyBotPackage/bot.py
PartyBotPackage/client.py
PartyBotPackage/defaults.py
PartyBotPackage/deviceauths.py
PartyBotPackage/sync.py
PartyBotPackage/web.py
PartyBotPackage-3.0.0.dist-info/METADATA
PartyBotPackage-3.0.0.dist-info/WHEEL
PartyBotPackage-3.0.0.dist-info/top_level.txt
PartyBotPackage-3.0.0.dist-info/RECORD
