Metadata-Version: 2.1
Name: PartyBotPackage
Version: 3.0.0
Summary: PartyBot in a PyPi package form to easily be ran on repl.
Home-page: https://partybot.net
Author: xMistt
Author-email: oli@partybot.net
Classifier: Programming Language :: Python :: 3
Classifier: License :: OSI Approved :: MIT License
Classifier: Operating System :: OS Independent
Requires-Python: >=3.5.3
Requires-Dist: aiofiles
Requires-Dist: aiohttp
Requires-Dist: fortnitepy
Requires-Dist: sanic
Requires-Dist: BenBotAsync
Requires-Dist: FortniteAPIAsync
Requires-Dist: crayons
Requires-Dist: aioconsole
